SklearnYuTensorflowJiqiXuexiShiyongZhinanDierBanFix1/README.md
SklearnYuTensorflowJiqiXuexiShiyongZhinanDierBanFix1/__init__.py
SklearnYuTensorflowJiqiXuexiShiyongZhinanDierBanFix1/__main__.py
SklearnYuTensorflowJiqiXuexiShiyongZhinanDierBanFix1/file.epub
SklearnYuTensorflowJiqiXuexiShiyongZhinanDierBanFix1/index.html
SklearnYuTensorflowJiqiXuexiShiyongZhinanDierBanFix1/css/__init__.py
SklearnYuTensorflowJiqiXuexiShiyongZhinanDierBanFix1/css/annotations.css
SklearnYuTensorflowJiqiXuexiShiyongZhinanDierBanFix1/css/main.css
SklearnYuTensorflowJiqiXuexiShiyongZhinanDierBanFix1/css/normalize.css
SklearnYuTensorflowJiqiXuexiShiyongZhinanDierBanFix1/css/popup.css
SklearnYuTensorflowJiqiXuexiShiyongZhinanDierBanFix1/font/__init__.py
SklearnYuTensorflowJiqiXuexiShiyongZhinanDierBanFix1/font/fontello.eot
SklearnYuTensorflowJiqiXuexiShiyongZhinanDierBanFix1/font/fontello.svg
SklearnYuTensorflowJiqiXuexiShiyongZhinanDierBanFix1/font/fontello.ttf
SklearnYuTensorflowJiqiXuexiShiyongZhinanDierBanFix1/font/fontello.woff
SklearnYuTensorflowJiqiXuexiShiyongZhinanDierBanFix1/img/__init__.py
SklearnYuTensorflowJiqiXuexiShiyongZhinanDierBanFix1/img/annotator-glyph-sprite.png
SklearnYuTensorflowJiqiXuexiShiyongZhinanDierBanFix1/img/annotator-icon-sprite.png
SklearnYuTensorflowJiqiXuexiShiyongZhinanDierBanFix1/img/apple-touch-icon.png
SklearnYuTensorflowJiqiXuexiShiyongZhinanDierBanFix1/img/cancelfullscreen.png
SklearnYuTensorflowJiqiXuexiShiyongZhinanDierBanFix1/img/close.png
SklearnYuTensorflowJiqiXuexiShiyongZhinanDierBanFix1/img/fullscreen.png
SklearnYuTensorflowJiqiXuexiShiyongZhinanDierBanFix1/img/loader.gif
SklearnYuTensorflowJiqiXuexiShiyongZhinanDierBanFix1/img/menu-icon.png
SklearnYuTensorflowJiqiXuexiShiyongZhinanDierBanFix1/img/save.png
SklearnYuTensorflowJiqiXuexiShiyongZhinanDierBanFix1/img/saved.png
SklearnYuTensorflowJiqiXuexiShiyongZhinanDierBanFix1/img/settings-s.png
SklearnYuTensorflowJiqiXuexiShiyongZhinanDierBanFix1/img/settings.png
sklearn_yu_tensorflow_jiqi_xuexi_shiyong_zhinan_dier_ban_fix1-2025.3.24.0.dist-info/METADATA
sklearn_yu_tensorflow_jiqi_xuexi_shiyong_zhinan_dier_ban_fix1-2025.3.24.0.dist-info/WHEEL
sklearn_yu_tensorflow_jiqi_xuexi_shiyong_zhinan_dier_ban_fix1-2025.3.24.0.dist-info/entry_points.txt
sklearn_yu_tensorflow_jiqi_xuexi_shiyong_zhinan_dier_ban_fix1-2025.3.24.0.dist-info/top_level.txt
sklearn_yu_tensorflow_jiqi_xuexi_shiyong_zhinan_dier_ban_fix1-2025.3.24.0.dist-info/RECORD
